sbol_factory/__init__.py
sbol_factory/code_generator.py
sbol_factory/create_module.py
sbol_factory/custom_eval.py
sbol_factory/json_ld_writer.py
sbol_factory/loader.py
sbol_factory/query.py
sbol_factory/sbol_factory.py
sbol_factory/sbol_factory_old.py
sbol_factory/shacl_validator.py
sbol_factory/uml_factory.py
sbol_factory/uml_factory_old.py
sbol_factory/umlviz.py
sbol_factory/utils.py
sbol_factory/rdf/SBO_OWL.rdf
sbol_factory/rdf/om-2.0.rdf
sbol_factory/rdf/prov-o.owl
sbol_factory/rdf/sbolowl3.rdf
sbol_factory/rdf/sd2.ttl
sbol_factory-1.1.2.dist-info/LICENSE.txt
sbol_factory-1.1.2.dist-info/METADATA
sbol_factory-1.1.2.dist-info/WHEEL
sbol_factory-1.1.2.dist-info/top_level.txt
sbol_factory-1.1.2.dist-info/RECORD
