Metadata-Version: 2.1
Name: sbol-factory
Version: 1.1.2
Summary: Ontology-driven data modeling
License-File: LICENSE.txt
Requires-Dist: sbol3 (>=1.0b12)
Requires-Dist: sparqlwrapper (>=1.8.5)
Requires-Dist: pyshacl (>=0.13.3)
Requires-Dist: python-dateutil (>=2.9)
Requires-Dist: requests
Requires-Dist: graphviz
Requires-Dist: pylatex
Requires-Dist: PyPDF2
